MANIFEST.in
README.txt
requirements.txt
setup.py
hpcli/__init__.py
hpcli/hpcli
hpcli.egg-info/PKG-INFO
hpcli.egg-info/SOURCES.txt
hpcli.egg-info/dependency_links.txt
hpcli.egg-info/requires.txt
hpcli.egg-info/top_level.txt
hpcli.egg-info/zip-safe
hpcli/hpclilib/__init__.py
hpcli/hpclilib/common.py
hpcli/hpclilib/docker.py
hpcli/hpclilib/ipython_generate.py
hpcli/hpclilib/login.py
hpcli/hpclilib/templates.py
hpcli/hpclilib/upload.py
hpcli/hpclilib/templates/python3-generic/inputschema.json
hpcli/hpclilib/templates/python3-generic/main.py
hpcli/hpclilib/templates/python3-generic/requirements.txt
hpcli/sdk/auth.py
hpcli/sdk/base.py
hpcli/sdk/common.py
hpcli/sdk/microservice_defn.py
hpcli/sdk/microservice_manager.py