Metadata-Version: 1.0
Name: hpcli
Version: 0.9.1
Summary: HighlyProbable SDK and CLI
Home-page: https://github.com/Tranquant/highlyprobable-cli
Author: Mehrdad Pazooki, David Briggs
Author-email: info@tranquant.com
License: MIT
Keywords: hpcli
Platform: UNKNOWN
